models/__init__.py
models/linreg.py
models/logreg.py
models/nn.py
nue-0.0.7.dist-info/LICENSE
nue-0.0.7.dist-info/METADATA
nue-0.0.7.dist-info/WHEEL
nue-0.0.7.dist-info/top_level.txt
nue-0.0.7.dist-info/RECORD
