Metadata-Version: 2.1
Name: nue
Version: 0.0.7
Summary: A deep learning framework sculpted for seamless implementation of models, geared towards entry level learners. 
Home-page: https://vxnuaj.github.io/nue/
Author: vxnuaj
Author-email: jv.100420@gmail.com
Classifier: Programming Language :: Python :: 3
Classifier: License :: OSI Approved :: MIT License
Classifier: Development Status :: 2 - Pre-Alpha
Classifier: Intended Audience :: Developers
Classifier: Intended Audience :: Education
License-File: LICENSE
Requires-Dist: numpy
Requires-Dist: pandas
Requires-Dist: matplotlib
